README.rst
bootstrap.py
buildout.cfg
example-buildout.cfg
setup.cfg
setup.py
Products/__init__.py
Products.Bitakora.egg-info/PKG-INFO
Products.Bitakora.egg-info/SOURCES.txt
Products.Bitakora.egg-info/dependency_links.txt
Products.Bitakora.egg-info/entry_points.txt
Products.Bitakora.egg-info/namespace_packages.txt
Products.Bitakora.egg-info/not-zip-safe
Products.Bitakora.egg-info/requires.txt
Products.Bitakora.egg-info/top_level.txt
Products/Bitakora/BUGS.txt
Products/Bitakora/Bitakora.py
Products/Bitakora/BitakoraCommunity.py
Products/Bitakora/CaptchasDotNet.py
Products/Bitakora/Comment.py
Products/Bitakora/EpozPostTidy.py
Products/Bitakora/IMPORT.txt
Products/Bitakora/PingMethodContainer.py
Products/Bitakora/PingbackObject.py
Products/Bitakora/Post.py
Products/Bitakora/Reference.py
Products/Bitakora/TODO.txt
Products/Bitakora/XMLImporter.py
Products/Bitakora/__init__.py
Products/Bitakora/akismet.py
Products/Bitakora/future.py
Products/Bitakora/refresh.txt
Products/Bitakora/tag.py
Products/Bitakora/tinymce_conf.py
Products/Bitakora/urllister.py
Products/Bitakora/utils.py
Products/Bitakora/img/icoBitakora.gif
Products/Bitakora/img/icoBitakoraCommunity.gif
Products/Bitakora/locale/es.po
Products/Bitakora/locale/eu.po
Products/Bitakora/locale/pl.po
Products/Bitakora/ui/BitakoraCommunity_add.dtml
Products/Bitakora/ui/Bitakora_add.dtml
Products/Bitakora/ui/Blog_edit.dtml
Products/Bitakora/ui/Post_add.dtml
Products/Bitakora/ui/Post_edit.dtml
Products/Bitakora/ui/Post_list.dtml
Products/Bitakora/ui/about.dtml
Products/Bitakora/ui/admin_blogs.dtml
Products/Bitakora/ui/admin_header.dtml
Products/Bitakora/ui/admin_users.dtml
Products/Bitakora/ui/archive.dtml
Products/Bitakora/ui/blog.css
Products/Bitakora/ui/captcha_control.dtml
Products/Bitakora/ui/comment_body.dtml
Products/Bitakora/ui/comment_email_template.dtml
Products/Bitakora/ui/comment_form.dtml
Products/Bitakora/ui/contact.dtml
Products/Bitakora/ui/contact_email_template.dtml
Products/Bitakora/ui/contents.dtml
Products/Bitakora/ui/downloadTXT.dtml
Products/Bitakora/ui/downloadWordPress.dtml
Products/Bitakora/ui/downloadXML.dtml
Products/Bitakora/ui/entry_body.dtml
Products/Bitakora/ui/entry_preview.dtml
Products/Bitakora/ui/feed.xml.dtml
Products/Bitakora/ui/index_html.dtml
Products/Bitakora/ui/localmenu.dtml
Products/Bitakora/ui/logged_in.dtml
