Metadata-Version: 1.1
Name: Products.Bitakora
Version: 1.1
Summary: UNKNOWN
Home-page: http://github.com/codesyntax/Products.Bitakora
Author: Mikel Larreategi
Author-email: mlarreategi@codesyntax.com
License: BSD
Keywords: zope blog community
Platform: UNKNOWN
Classifier: Programming Language :: Python
